artisinal_integers/__init__.py
artisinal_integers-0.2.1.dist-info/METADATA
artisinal_integers-0.2.1.dist-info/WHEEL
artisinal_integers-0.2.1.dist-info/top_level.txt
artisinal_integers-0.2.1.dist-info/RECORD
