Metadata-Version: 2.1
Name: artisinal-integers
Version: 0.2.1
Summary: Get unique artisinal integers, locally sourced!
Home-page: http://github.com/micahwalter/artisinal_integers
Author: Micah Walter
Author-email: micah@micahwalter.com
License: MIT
Platform: UNKNOWN
Requires-Dist: requests
